MANIFEST.in
README
README.md
setup.py
adsmt/README.md
adsmt/__init__.py
adsmt/adcli
adsmt/cli.py
adsmt.egg-info/PKG-INFO
adsmt.egg-info/SOURCES.txt
adsmt.egg-info/dependency_links.txt
adsmt.egg-info/entry_points.txt
adsmt.egg-info/not-zip-safe
adsmt.egg-info/requires.txt
adsmt.egg-info/top_level.txt
adsmt/manager/__init__.py
adsmt/simcli/__init__.py