Metadata-Version: 1.1
Name: adsmt
Version: 1.0.10
Summary: Active Directory Simple Management Toolkit
Home-page: https://bitbucket.org/deniskhodus/adsmt
Author: Denis Khodus
Author-email: deniskhodus@gmail.com
License: MIT
Keywords: ad active directory samba manage console cli
Platform: UNKNOWN
Classifier: Development Status :: 5 - Production/Stable
Classifier: License :: OSI Approved :: Mozilla Public License 2.0 (MPL 2.0)
Classifier: Programming Language :: Python :: 2
Classifier: Programming Language :: Python :: 3
Classifier: Topic :: System :: Systems Administration
Classifier: Topic :: System :: Systems Administration :: Authentication/Directory
Classifier: Topic :: System :: Systems Administration :: Authentication/Directory :: LDAP
